{
  "routes": [
    {
      "path": "",
      "name": "BASE"
    },
    {
      "path": "@/notes/testIndex.vue",
      "name": "测试"
    },
    {
      "path": "@/notes/01base/01html/01.md",
      "name": "html标签"
    },
    {
      "path": "@/notes/01base/01html/02.md",
      "name": "html5标签"
    },
    {
      "path": "@/notes/01base/01html/03.md",
      "name": "html属性"
    },
    {
      "path": "@/notes/01base/01html/04.md",
      "name": "html事件"
    },
    {
      "path": "@/notes/01base/01html/05.md",
      "name": "html5事件"
    },
    {
      "path": "@/notes/01base/01html/06.md",
      "name": "http方法消息"
    },
    {
      "path": "@/notes/01base/01html/07.md",
      "name": "html补充"
    },
    {
      "path": "@/notes/01base/01html/08.md",
      "name": "html案例"
    },
    {
      "path": "@/notes/01base/02css/01.md",
      "name": "css基础属性"
    },
    {
      "path": "@/notes/01base/02css/02.md",
      "name": "css表格定位等属性"
    },
    {
      "path": "@/notes/01base/02css/03.md",
      "name": "css3补充属性"
    },
    {
      "path": "@/notes/01base/02css/04.md",
      "name": "css3盒子线框等属性"
    },
    {
      "path": "@/notes/01base/02css/05.md",
      "name": "css3多媒体过渡等属性"
    },
    {
      "path": "@/notes/01base/02css/06.md",
      "name": "css选择器及函数"
    },
    {
      "path": "@/notes/01base/02css/07.md",
      "name": "css补充及案例"
    },
    {
      "path": "",
      "name": "JavaScript"
    },
    {
      "path": "@/notes/01base/03javascript/01.md",
      "name": "简介和使用"
    },
    {
      "path": "@/notes/01base/03javascript/02.md",
      "name": "基础类型"
    },
    {
      "path": "@/notes/01base/03javascript/03.md",
      "name": "操作符"
    },
    {
      "path": "@/notes/01base/03javascript/04.md",
      "name": "语句和函数"
    },
    {
      "path": "@/notes/01base/03javascript/05.md",
      "name": "变量、作用域和内存"
    },
    {
      "path": "@/notes/01base/03javascript/06.md",
      "name": "对象、时间、正则"
    },
    {
      "path": "@/notes/01base/03javascript/07.md",
      "name": "数组、函数"
    },
    {
      "path": "@/notes/01base/03javascript/08.md",
      "name": "基本包装类型"
    },
    {
      "path": "@/notes/01base/03javascript/09.md",
      "name": "面向对象设计"
    },
    {
      "path": "@/notes/01base/03javascript/10.md",
      "name": "函数表达式"
    },
    {
      "path": "@/notes/01base/03javascript/11.md",
      "name": "BOM"
    },
    {
      "path": "@/notes/01base/03javascript/12.md",
      "name": "客户端检测"
    },
    {
      "path": "@/notes/01base/03javascript/13.md",
      "name": "DOM 类型"
    },
    {
      "path": "@/notes/01base/03javascript/14.md",
      "name": "DOM 操作"
    },
    {
      "path": "@/notes/01base/03javascript/15.md",
      "name": "DOM 扩展"
    },
    {
      "path": "@/notes/01base/03javascript/16.md",
      "name": "DOM2 和 DOM3"
    },
    {
      "path": "@/notes/01base/03javascript/17.md",
      "name": "事件"
    },
    {
      "path": "@/notes/01base/03javascript/18.md",
      "name": "表单脚本"
    },
    {
      "path": "@/notes/01base/03javascript/19.md",
      "name": "Canvas 绘图"
    },
    {
      "path": "@/notes/01base/03javascript/20.md",
      "name": "Html5脚本编程"
    },
    {
      "path": "@/notes/01base/03javascript/21.md",
      "name": "XML、JSON和AJAX"
    },
    {
      "path": "@/notes/01base/03javascript/22.md",
      "name": "高级技巧与新兴API"
    },
    {
      "path": "",
      "name": "typeScript"
    },
    {
      "path": "@/notes/01base/04typescript/01.md",
      "name": "简介和使用"
    },
    {
      "path": "@/notes/01base/04typescript/02.md",
      "name": "基础类型"
    },
    {
      "path": "@/notes/01base/04typescript/03.md",
      "name": "变量声明"
    },
    {
      "path": "@/notes/01base/04typescript/04.md",
      "name": "接口"
    },
    {
      "path": "@/notes/01base/04typescript/05.md",
      "name": "类"
    },
    {
      "path": "@/notes/01base/04typescript/06.md",
      "name": "函数"
    },
    {
      "path": "@/notes/01base/04typescript/07.md",
      "name": "泛型"
    },
    {
      "path": "@/notes/01base/04typescript/08.md",
      "name": "枚举"
    },

    {
      "path": "@/notes/01base/04typescript/09.md",
      "name": "类型推论"
    },
    {
      "path": "@/notes/01base/04typescript/10.md",
      "name": "类型兼容性"
    },
    {
      "path": "@/notes/01base/04typescript/11.md",
      "name": "高级类型"
    },
    {
      "path": "@/notes/01base/04typescript/12.md",
      "name": "Symbols"
    },
    {
      "path": "@/notes/01base/04typescript/13.md",
      "name": "迭代器和生成器"
    },

    {
      "path": "@/notes/01base/04typescript/14.md",
      "name": "模块"
    },
    {
      "path": "@/notes/01base/04typescript/15.md",
      "name": "命名空间"
    },
    {
      "path": "@/notes/01base/04typescript/16.md",
      "name": "命名空间和模块"
    },
    {
      "path": "@/notes/01base/04typescript/17.md",
      "name": "模块解析"
    },
    {
      "path": "@/notes/01base/04typescript/18.md",
      "name": "声明合并"
    },

    {
      "path": "@/notes/01base/04typescript/19.md",
      "name": "JSX"
    },
    {
      "path": "@/notes/01base/04typescript/20.md",
      "name": "装饰器"
    },
    {
      "path": "@/notes/01base/04typescript/21.md",
      "name": "Mixins"
    },
    {
      "path": "@/notes/01base/04typescript/22.md",
      "name": "三斜线指令"
    },
    {
      "path": "@/notes/01base/04typescript/23.md",
      "name": "Javascript文件类型检查"
    },
    {
      "path": "",
      "name": "Vue"
    },
    {
      "path": "@/notes/02vue/01vue/01.md",
      "name": "Vue介绍"
    },
    {
      "path": "@/notes/02vue/01vue/02.md",
      "name": "Vue实例"
    },
    {
      "path": "@/notes/02vue/01vue/03.md",
      "name": "模板语法"
    },
    {
      "path": "@/notes/02vue/01vue/04.md",
      "name": "计算属性和侦听器"
    },
    {
      "path": "@/notes/02vue/01vue/05.md",
      "name": "Class与Style绑定"
    },
    {
      "path": "@/notes/02vue/01vue/06.md",
      "name": "条件渲染"
    },
    {
      "path": "@/notes/02vue/01vue/07.md",
      "name": "列表渲染"
    },
    {
      "path": "@/notes/02vue/01vue/08.md",
      "name": "事件处理"
    },
    {
      "path": "@/notes/02vue/01vue/09.md",
      "name": "表单输入绑定"
    },
    {
      "path": "@/notes/02vue/01vue/10.md",
      "name": "组件基础"
    },
    {
      "path": "@/notes/02vue/01vue/11.md",
      "name": "组件注册"
    },
    {
      "path": "@/notes/02vue/01vue/12.md",
      "name": "组件Prop"
    },
    {
      "path": "@/notes/02vue/01vue/13.md",
      "name": "组件自定义事件"
    },
    {
      "path": "@/notes/02vue/01vue/14.md",
      "name": "组件插槽"
    },
    {
      "path": "@/notes/02vue/01vue/15.md",
      "name": "组件动态异步"
    },
    {
      "path": "@/notes/02vue/01vue/16.md",
      "name": "组件处理边界情况"
    },
    {
      "path": "@/notes/02vue/01vue/17.md",
      "name": "单元素/组件的过渡"
    },
    {
      "path": "@/notes/02vue/01vue/18.md",
      "name": "多元素/组件的过渡"
    },
    {
      "path": "@/notes/02vue/01vue/19.md",
      "name": "列表过渡"
    },
    {
      "path": "@/notes/02vue/01vue/20.md",
      "name": "状态过渡"
    },
    {
      "path": "@/notes/02vue/01vue/21.md",
      "name": "混入"
    },
    {
      "path": "@/notes/02vue/01vue/22.md",
      "name": "自定义插件"
    },
    {
      "path": "@/notes/02vue/01vue/23.md",
      "name": "渲染函数&JSX"
    },
    {
      "path": "@/notes/02vue/01vue/24.md",
      "name": "插件"
    },
    {
      "path": "@/notes/02vue/01vue/25.md",
      "name": "过滤器"
    },
    {
      "path": "",
      "name": "Vues"
    },
    {
      "path": "@/notes/02vue/02router/01.md",
      "name": "router起步"
    },
    {
      "path": "@/notes/02vue/02router/02.md",
      "name": "router基础"
    },
    {
      "path": "@/notes/02vue/02router/03.md",
      "name": "router导航守卫"
    },
    {
      "path": "@/notes/02vue/02router/04.md",
      "name": "router进阶"
    },
    {
      "path": "@/notes/02vue/03vuex/01.md",
      "name": "vuex基础"
    },
    {
      "path": "@/notes/02vue/03vuex/02.md",
      "name": "vuex-State"
    },
    {
      "path": "@/notes/02vue/03vuex/03.md",
      "name": "vuex-Getter"
    },
    {
      "path": "@/notes/02vue/03vuex/04.md",
      "name": "vuex-Mutation"
    },
    {
      "path": "@/notes/02vue/03vuex/05.md",
      "name": "vuex-Action"
    },
    {
      "path": "@/notes/02vue/03vuex/06.md",
      "name": "vuex-Module"
    },
    {
      "path": "@/notes/02vue/04ssr/01.md",
      "name": "ssr基础"
    },
    {
      "path": "@/notes/02vue/05axios/01.md",
      "name": "axios基础"
    },
    {
      "path": "@/notes/02vue/05axios/02.md",
      "name": "axios进阶"
    },
    {
      "path": "",
      "name": "Node"
    },
    {
      "path": "@/notes/03node/01node/01.md",
      "name": "node基础"
    },
    {
      "path": "@/notes/03node/01node/02.md",
      "name": "nodeEventEmitter"
    },
    {
      "path": "@/notes/03node/01node/03.md",
      "name": "nodeBuffer(缓冲区)"
    },
    {
      "path": "@/notes/03node/01node/04.md",
      "name": "nodeStream(流)"
    },
    {
      "path": "@/notes/03node/01node/05.md",
      "name": "node模块函数路由"
    },
    {
      "path": "@/notes/03node/01node/06.md",
      "name": "node全局对象和util"
    },
    {
      "path": "@/notes/03node/01node/07.md",
      "name": "node文件系统"
    },
    {
      "path": "@/notes/03node/01node/08.md",
      "name": "node文件系统"
    },
    {
      "path": "@/notes/03node/01node/09.md",
      "name": "Express 框架"
    },
    {
      "path": "@/notes/03node/01node/10.md",
      "name": "多进程"
    },
    {
      "path": "@/notes/03node/01node/11.md",
      "name": "MySQL"
    },
    {
      "path": "@/notes/03node/01node/12.md",
      "name": "MongoDB"
    },
    {
      "path": "@/notes/03node/02webpack/01.md",
      "name": "webpack基础"
    },
    {
      "path": "@/notes/03node/03npm/01.md",
      "name": "npm基础"
    }
  ]
}